[{"简":"安全系数","繁":"安全係數"},{"简":"保险系数","繁":"保險係數"},{"简":"菜系","繁":"菜系"},{"简":"参照系","繁":"參照系"},{"简":"嫡系","繁":"嫡系"},{"简":"父系","繁":"父系"},{"简":"干系","繁":"干係"},{"简":"感慨系之","繁":"感慨繫之"},{"简":"根系","繁":"根系"},{"简":"公共关系","繁":"公共關係"},{"简":"关系","繁":"關係"},{"简":"关系户","繁":"關係戶"},{"简":"关系网","繁":"關係網"},{"简":"海外关系","繁":"海外關係"},{"简":"河系","繁":"河系"},{"简":"拉关系","繁":"拉關係"},{"简":"联系","繁":"聯繫"},{"简":"联系人","繁":"聯繫人"},{"简":"两性关系","繁":"兩性關係"},{"简":"没关系","繁":"沒關係"},{"简":"母系","繁":"母系"},{"简":"男女关系","繁":"男女關係"},{"简":"派系","繁":"派系"},{"简":"旁系","繁":"旁系"},{"简":"品系","繁":"品系"},{"简":"谱系","繁":"譜系"},{"简":"牵系","繁":"牽繫"},{"简":"全球定位系统","繁":"全球定位系統"},{"简":"确系","繁":"確係"},{"简":"裙带关系","繁":"裙帶關係"},{"简":"群众关系","繁":"群眾關係"},{"简":"山系","繁":"山系"},{"简":"社会关系","繁":"社會關係"},{"简":"生产关系","繁":"生產關係"},{"简":"世系","繁":"世系"},{"简":"市场体系","繁":"市場體系"},{"简":"水系","繁":"水系"},{"简":"思想体系","繁":"思想體系"},{"简":"太阳系","繁":"太陽系"},{"简":"体系","繁":"體系"},{"简":"维系","繁":"維繫"},{"简":"系列片","繁":"系列片"},{"简":"系列","繁":"系列"},{"简":"系列化","繁":"系列化"},{"简":"系列剧","繁":"系列劇"},{"简":"系铃人","繁":"繫鈴人"},{"简":"系念","繁":"繫念"},{"简":"系数","繁":"係數"},{"简":"系统","繁":"系統"},{"简":"系统工程","繁":"系統工程"},{"简":"系统化","繁":"系統化"},{"简":"系统性","繁":"系統性"},{"简":"星系","繁":"星系"},{"简":"学系","繁":"學系"},{"简":"循环系统","繁":"循環系統"},{"简":"一系列","繁":"一系列"},{"简":"音系","繁":"音系"},{"简":"银河系","繁":"銀河系"},{"简":"直系","繁":"直系"},{"简":"直系亲属","繁":"直系親屬"},{"简":"转关系","繁":"轉關係"},{"简":"子系统","繁":"子系統"},{"简":"自成体系","繁":"自成體系"},{"简":"组织关系","繁":"組織關係"},{"简":"坐标系","繁":"坐標系"}]